torch_optim_sparse/__init__.py
torch_optim_sparse/sparser_adam.py
torch_optim_sparse/sparser_adamw.py
torch_optim_sparse/sparser_sgd.py
torch_optim_sparse/sparser_sgdw.py
torch_optim_sparse-0.1.3.dist-info/LICENSE.md
torch_optim_sparse-0.1.3.dist-info/WHEEL
torch_optim_sparse-0.1.3.dist-info/METADATA
torch_optim_sparse-0.1.3.dist-info/RECORD
