Metadata-Version: 2.1
Name: torch-optim-sparse
Version: 0.1.3
Summary: PyTorch optimizers with sparse momentum and weight decay
Author: Karl Higley
Author-email: kmhigley@gmail.com
Requires-Python: >=3.7,<4.0
Classifier: Programming Language :: Python :: 3
Classifier: Programming Language :: Python :: 3.7
Classifier: Programming Language :: Python :: 3.8
Requires-Dist: torch (>=1.6.0,<2.0.0)
